jconfig/__init__.py
jconfig/base.py
jconfig/jconfig.py
jconfig/memory.py
vk_api/__init__.py
vk_api/audio.py
vk_api/audio_url_decoder.py
vk_api/bot_longpoll.py
vk_api/enums.py
vk_api/exceptions.py
vk_api/execute.py
vk_api/keyboard.py
vk_api/longpoll.py
vk_api/requests_pool.py
vk_api/streaming.py
vk_api/tools.py
vk_api/upload.py
vk_api/utils.py
vk_api/vk_api.py
vk_api-11.9.8.dist-info/LICENSE
vk_api-11.9.8.dist-info/METADATA
vk_api-11.9.8.dist-info/WHEEL
vk_api-11.9.8.dist-info/top_level.txt
vk_api-11.9.8.dist-info/RECORD
