Metadata-Version: 2.1
Name: vk-api
Version: 11.9.8
Summary: Python модуль для создания скриптов для социальной сети Вконтакте (vk.com API wrapper)
Home-page: https://github.com/python273/vk_api
Download-URL: https://github.com/python273/vk_api/archive/v11.9.8.zip
Author: python273
Author-email: vk_api@python273.pw
License: Apache License, Version 2.0, see LICENSE file
Platform: UNKNOWN
Classifier: License :: OSI Approved :: Apache Software License
Classifier: Operating System :: OS Independent
Classifier: Programming Language :: Python
Classifier: Programming Language :: Python :: 3
Classifier: Programming Language :: Python :: 3.6
Classifier: Programming Language :: Python :: 3.7
Classifier: Programming Language :: Python :: 3.8
Classifier: Programming Language :: Python :: 3.9
Classifier: Programming Language :: Python :: 3.10
Provides-Extra: vkstreaming
Provides-Extra: vkaudio
License-File: LICENSE
